eemeter/__init__.py
eemeter/__version__.py
eemeter/common/__init__.py
eemeter/common/abstract_data_processor.py
eemeter/common/abstract_data_settings.py
eemeter/common/adaptive_loss.py
eemeter/common/adaptive_loss_tck.py
eemeter/common/const.py
eemeter/common/data_settings.py
eemeter/common/test_data.py
eemeter/common/utils.py
eemeter/drmeter/__init__.py
eemeter/drmeter/data.py
eemeter/drmeter/model.py
eemeter/eemeter/__init__.py
eemeter/eemeter/common/__init__.py
eemeter/eemeter/common/data_processor_utilities.py
eemeter/eemeter/common/exceptions.py
eemeter/eemeter/common/features.py
eemeter/eemeter/common/sufficiency_criteria.py
eemeter/eemeter/common/transform.py
eemeter/eemeter/common/warnings.py
eemeter/eemeter/models/__init__.py
eemeter/eemeter/models/billing/__init__.py
eemeter/eemeter/models/billing/data.py
eemeter/eemeter/models/billing/model.py
eemeter/eemeter/models/billing/plot.py
eemeter/eemeter/models/daily/__init__.py
eemeter/eemeter/models/daily/data.py
eemeter/eemeter/models/daily/fit_base_models.py
eemeter/eemeter/models/daily/model.py
eemeter/eemeter/models/daily/objective_function.py
eemeter/eemeter/models/daily/optimize.py
eemeter/eemeter/models/daily/optimize_results.py
eemeter/eemeter/models/daily/parameters.py
eemeter/eemeter/models/daily/plot.py
eemeter/eemeter/models/daily/base_models/__init__.py
eemeter/eemeter/models/daily/base_models/c_hdd_tidd.py
eemeter/eemeter/models/daily/base_models/full_model.py
eemeter/eemeter/models/daily/base_models/hdd_tidd_cdd.py
eemeter/eemeter/models/daily/base_models/tidd.py
eemeter/eemeter/models/daily/utilities/__init__.py
eemeter/eemeter/models/daily/utilities/base_model.py
eemeter/eemeter/models/daily/utilities/config.py
eemeter/eemeter/models/daily/utilities/ellipsoid_test.py
eemeter/eemeter/models/daily/utilities/selection_criteria.py
eemeter/eemeter/models/hourly/__init__.py
eemeter/eemeter/models/hourly/data.py
eemeter/eemeter/models/hourly/derivatives.py
eemeter-4.0.8.dist-info/LICENSE
eemeter-4.0.8.dist-info/METADATA
eemeter-4.0.8.dist-info/WHEEL
eemeter-4.0.8.dist-info/entry_points.txt
eemeter-4.0.8.dist-info/top_level.txt
eemeter-4.0.8.dist-info/RECORD
