Metadata-Version: 2.1
Name: eemeter
Version: 4.0.8
Summary: Open Energy Efficiency Meter
Home-page: http://github.com/openeemeter/eemeter
Author: Phil Ngo
Author-email: admin@openee.io
License: Apache 2.0
Classifier: License :: OSI Approved :: Apache Software License
Classifier: Programming Language :: Python
Classifier: Programming Language :: Python :: 3
Classifier: Programming Language :: Python :: 3.8
Classifier: Programming Language :: Python :: 3.9
Classifier: Programming Language :: Python :: 3.10
Classifier: Programming Language :: Python :: 3.11
Classifier: Programming Language :: Python :: 3.12
License-File: LICENSE
Requires-Dist: click
Requires-Dist: pandas>=1.0.0
Requires-Dist: statsmodels
Requires-Dist: scipy
Requires-Dist: numba
Requires-Dist: nlopt
Requires-Dist: pydantic>=2.0
Requires-Dist: attrs
Requires-Dist: requests
